rootdir/__init__.py
rootdir-0.1.3.dist-info/METADATA
rootdir-0.1.3.dist-info/WHEEL
rootdir-0.1.3.dist-info/top_level.txt
rootdir-0.1.3.dist-info/RECORD
