Metadata-Version: 2.1
Name: rootdir
Version: 0.1.3
Summary: get python root directory easily
Home-page: https://github.com/meansoup/rootdir
Author: meansoup
Author-email: alsrnr1210@gmail.com
License: UNKNOWN
Platform: UNKNOWN
